cpm_torch/CPM.py
cpm_torch/CPM_Image.py
cpm_torch/CPM_Map.py
cpm_torch/CPM_main.ipynb
cpm_torch/__init__.py
cpm_torch-0.1.2.dist-info/LICENSE
cpm_torch-0.1.2.dist-info/METADATA
cpm_torch-0.1.2.dist-info/WHEEL
cpm_torch-0.1.2.dist-info/RECORD
